some_math/__init__.py
some_math/fit_circle.py
some_math/fit_line.py
some_math/fit_plane.py
some_math/lin_alg.py
some_math/lin_reg.py
some_math/process_capability.py
some_math/quaternion.py
some_math/geo/__init__.py
some_math/geo/cuboid.py
some_math/geo/line_segment.py
some_math/geo/plane.py
some_math/geo/points.py
some_math/geo/points_2D.py
some_math/geo/points_3D.py
some_math-0.0.3.dist-info/METADATA
some_math-0.0.3.dist-info/RECORD
some_math-0.0.3.dist-info/WHEEL
some_math-0.0.3.dist-info/top_level.txt
tests/__init__.py
tests/test_cuboid.py
tests/test_fit_circle.py
tests/test_fit_plane.py
tests/test_geo.py
tests/test_lin_alg.py
tests/test_line_segment.py
tests/test_plane.py
tests/test_points_2D.py
tests/test_points_3D.py
tests/test_process_capability.py
tests/test_quaternion.py
