Metadata-Version: 2.1
Name: some-math
Version: 0.0.3
Summary: some math routines
Home-page: https://bitbucket.org/hirschbeutel/some_math
Author: hirschbeutel
Author-email: hirschbeutel@gmail.com
License: MIT
Platform: UNKNOWN
